Metadata-Version: 2.1
Name: example-package-vijayGigayasa1
Version: 0.0.2
Summary: A new small example package
Author-email: VijayGigayasa1 <vijaya@gigayasa.com>
Project-URL: Homepage, https://github.com/pypa/sampleproject
Project-URL: Bug Tracker, https://github.com/pypa/sampleproject/issues
Classifier: Programming Language :: Python :: 3
Classifier: License :: OSI Approved :: MIT License
Classifier: Operating System :: OS Independent
Requires-Python: >=3.7
License-File: LICENSE
Requires-Dist: tensorflow
Requires-Dist: numpy
Requires-Dist: matplotlib
